dx_punch/__init__.py
dx_punch/EC2/__init__.py
dx_punch/EC2/column.py
dx_punch/EC2/exceptions.py
dx_punch/EC2/forces.py
dx_punch/EC2/perimeters.py
dx_punch/EC2/shear_reinforcement.py
dx_punch/EC2/slab.py
dx_punch/bin/__init__.py
dx_punch/bin/dx_punch.py
dx_punch-1.0.0.dist-info/LICENSE
dx_punch-1.0.0.dist-info/METADATA
dx_punch-1.0.0.dist-info/WHEEL
dx_punch-1.0.0.dist-info/top_level.txt
dx_punch-1.0.0.dist-info/RECORD
