Metadata-Version: 2.1
Name: dx-punch
Version: 1.0.0
Summary: Punching-shear calculation package
Home-page: https://gitlab.com/d-e/dx-punch
Author: Konstantinos Demartinos
Author-email: kostas@d-e.gr
Maintainer: demetriou engineering ltd.
Maintainer-email: mike@d-e.gr
License: AGPLv3+
Keywords: structural-design,eurocode,punching-shear
Platform: UNKNOWN
Classifier: Programming Language :: Python :: 3.6
Classifier: License :: OSI Approved :: GNU Affero General Public License v3 or later (AGPLv3+)
Classifier: Operating System :: OS Independent
Classifier: Topic :: Scientific/Engineering
Requires-Dist: dx-eurocode (<2.0.0,>=1.0.0)
Requires-Dist: pandas (==0.23.4)
Requires-Dist: matplotlib (==2.2.2)
